rtl/fifo_mem.v
`timescale 1ns / 1ps
//////////////////////////////////////////////////////////////////////////////////
// Company: 
// Engineer: 
// 
// Create Date: 30.07.2025 21:15:53
// Design Name: 
// Module Name: fifo_mem
// Project Name: 
// Target Devices: 
// Tool Versions: 
// Description: 
// 
// Dependencies: 
// 
// Revision:
// Revision 0.01 - File Created
// Additional Comments:
// 
//////////////////////////////////////////////////////////////////////////////////

module fifo_mem #(parameter DEPTH=8, DATA_WIDTH=8, PTR_WIDTH=3) (
  input wclk, w_en, rclk, r_en,
  input [PTR_WIDTH:0] b_wptr, b_rptr,
  input [DATA_WIDTH-1:0] data_in,
  input full, empty,
  output reg [DATA_WIDTH-1:0] data_out
);
  reg [DATA_WIDTH-1:0] fifo[0:DEPTH-1];
  
  always@(posedge wclk) begin
    if(w_en & !full) begin
      fifo[b_wptr[PTR_WIDTH-1:0]] <= data_in;
    end
  end
  /*
  always@(posedge rclk) begin
    if(r_en & !empty) begin
      data_out <= fifo[b_rptr[PTR_WIDTH-1:0]];
    end
  end
  */
  assign data_out = fifo[b_rptr[PTR_WIDTH-1:0]];
endmodule

fifo/fifo.srcs/sources_1/new/rptr_handler.v
`timescale 1ns / 1ps
//////////////////////////////////////////////////////////////////////////////////
// Company: 
// Engineer: 
// 
// Create Date: 30.07.2025 21:15:34
// Design Name: 
// Module Name: rptr_handler
// Project Name: 
// Target Devices: 
// Tool Versions: 
// Description: 
// 
// Dependencies: 
// 
// Revision:
// Revision 0.01 - File Created
// Additional Comments:
// 
//////////////////////////////////////////////////////////////////////////////////

module rptr_handler #(parameter PTR_WIDTH=3) (
  input rclk, rrst_n, r_en,
  input [PTR_WIDTH:0] g_wptr_sync,
  output reg [PTR_WIDTH:0] b_rptr, g_rptr,
  output reg empty
);

  reg [PTR_WIDTH:0] b_rptr_next;
  reg [PTR_WIDTH:0] g_rptr_next;

  assign b_rptr_next = b_rptr+(r_en & !empty);
  assign g_rptr_next = (b_rptr_next >>1)^b_rptr_next;
  assign rempty = (g_wptr_sync == g_rptr_next);
  
  always@(posedge rclk or negedge rrst_n) begin
    if(!rrst_n) begin
      b_rptr <= 0;
      g_rptr <= 0;
    end
    else begin
      b_rptr <= b_rptr_next;
      g_rptr <= g_rptr_next;
    end
  end
  
  always@(posedge rclk or negedge rrst_n) begin
    if(!rrst_n) empty <= 1;
    else        empty <= rempty;
  end
endmodule

rtl/wptr_handler.v
`timescale 1ns / 1ps
//////////////////////////////////////////////////////////////////////////////////
// Company: 
// Engineer: 
// 
// Create Date: 30.07.2025 21:15:14
// Design Name: 
// Module Name: wptr_handler
// Project Name: 
// Target Devices: 
// Tool Versions: 
// Description: 
// 
// Dependencies: 
// 
// Revision:
// Revision 0.01 - File Created
// Additional Comments:
// 
//////////////////////////////////////////////////////////////////////////////////


module wptr_handler #(parameter PTR_WIDTH=3) (
  input wclk, wrst_n, w_en,
  input [PTR_WIDTH:0] g_rptr_sync,
  output reg [PTR_WIDTH:0] b_wptr, g_wptr,
  output reg full
);

  reg [PTR_WIDTH:0] b_wptr_next;
  reg [PTR_WIDTH:0] g_wptr_next;
   
  reg wrap_around;
  wire wfull;
  
  assign b_wptr_next = b_wptr+(w_en & !full);
  assign g_wptr_next = (b_wptr_next >>1)^b_wptr_next;
  
  always@(posedge wclk or negedge wrst_n) begin
    if(!wrst_n) begin
      b_wptr <= 0; // set default value
      g_wptr <= 0;
    end
    else begin
      b_wptr <= b_wptr_next; // incr binary write pointer
      g_wptr <= g_wptr_next; // incr gray write pointer
    end
  end
  
  always@(posedge wclk or negedge wrst_n) begin
    if(!wrst_n) full <= 0;
    else        full <= wfull;
  end

  assign wfull = (g_wptr_next == {~g_rptr_sync[PTR_WIDTH:PTR_WIDTH-1], g_rptr_sync[PTR_WIDTH-2:0]});

endmodule

rtl/synchronizer.v
`timescale 1ns / 1ps
//////////////////////////////////////////////////////////////////////////////////
// Company: 
// Engineer: 
// 
// Create Date: 30.07.2025 21:15:02
// Design Name: 
// Module Name: synchronizer
// Project Name: 
// Target Devices: 
// Tool Versions: 
// Description: 
// 
// Dependencies: 
// 
// Revision:
// Revision 0.01 - File Created
// Additional Comments:
// 
//////////////////////////////////////////////////////////////////////////////////


module synchronizer #(parameter WIDTH=3) (input clk, rst_n, [WIDTH:0] d_in, output reg [WIDTH:0] d_out);
  reg [WIDTH:0] q1;
  always@(posedge clk) begin
    if(!rst_n) begin
      q1 <= 0;
      d_out <= 0;
    end
    else begin
      q1 <= d_in;
      d_out <= q1;
    end
  end
endmodule

rtl/async_fifo.v
`timescale 1ns / 1ps
//////////////////////////////////////////////////////////////////////////////////
// Company: 
// Engineer: 
// 
// Create Date: 30.07.2025 21:16:26
// Design Name: 
// Module Name: asynchronous_fifo
// Project Name: 
// Target Devices: 
// Tool Versions: 
// Description: 
// 
// Dependencies: 
// 
// Revision:
// Revision 0.01 - File Created
// Additional Comments:
// 
//////////////////////////////////////////////////////////////////////////////////


`include "synchronizer.v"
`include "wptr_handler.v"
`include "rptr_handler.v"
`include "fifo_mem.v"

module asynchronous_fifo #(parameter DEPTH=8, DATA_WIDTH=8) (
  input wclk, wrst_n,
  input rclk, rrst_n,
  input w_en, r_en,
  input [DATA_WIDTH-1:0] data_in,
  output reg [DATA_WIDTH-1:0] data_out,
  output reg full, empty
);
  
  parameter PTR_WIDTH = $clog2(DEPTH);
 
  reg [PTR_WIDTH:0] g_wptr_sync, g_rptr_sync;
  reg [PTR_WIDTH:0] b_wptr, b_rptr;
  reg [PTR_WIDTH:0] g_wptr, g_rptr;

  wire [PTR_WIDTH-1:0] waddr, raddr;

  synchronizer #(PTR_WIDTH) sync_wptr (rclk, rrst_n, g_wptr, g_wptr_sync); //write pointer to read clock domain
  synchronizer #(PTR_WIDTH) sync_rptr (wclk, wrst_n, g_rptr, g_rptr_sync); //read pointer to write clock domain 
  
  wptr_handler #(PTR_WIDTH) wptr_h(wclk, wrst_n, w_en,g_rptr_sync,b_wptr,g_wptr,full);
  rptr_handler #(PTR_WIDTH) rptr_h(rclk, rrst_n, r_en,g_wptr_sync,b_rptr,g_rptr,empty);
  fifo_mem fifom(wclk, w_en, rclk, r_en,b_wptr, b_rptr, data_in,full,empty, data_out);

endmodule

fifo/fifo.srcs/sim_1/new/async_fifo_TB.v
`timescale 1ns / 1ps
//////////////////////////////////////////////////////////////////////////////////
// Company: 
// Engineer: 
// 
// Create Date: 30.07.2025 21:16:43
// Design Name: 
// Module Name: async_fifo_TB
// Project Name: 
// Target Devices: 
// Tool Versions: 
// Description: 
// 
// Dependencies: 
// 
// Revision:
// Revision 0.01 - File Created
// Additional Comments:
// 
//////////////////////////////////////////////////////////////////////////////////

module async_fifo_TB;

  parameter DATA_WIDTH = 8;

  wire [DATA_WIDTH-1:0] data_out;
  wire full;
  wire empty;
  reg [DATA_WIDTH-1:0] data_in;
  reg w_en, wclk, wrst_n;
  reg r_en, rclk, rrst_n;

  // Queue to push data_in
  reg [DATA_WIDTH-1:0] wdata_q[$], wdata;

  asynchronous_fifo as_fifo (wclk, wrst_n,rclk, rrst_n,w_en,r_en,data_in,data_out,full,empty);

  always #10ns wclk = ~wclk;
  always #35ns rclk = ~rclk;
  
  initial begin
    wclk = 1'b0; wrst_n = 1'b0;
    w_en = 1'b0;
    data_in = 0;
    
    repeat(10) @(posedge wclk);
    wrst_n = 1'b1;

    repeat(2) begin
      for (int i=0; i<30; i++) begin
        @(posedge wclk iff !full);
        w_en = (i%2 == 0)? 1'b1 : 1'b0;
        if (w_en) begin
          data_in = $urandom;
          wdata_q.push_back(data_in);
        end
      end
      #50;
    end
  end

  initial begin
    rclk = 1'b0; rrst_n = 1'b0;
    r_en = 1'b0;

    repeat(20) @(posedge rclk);
    rrst_n = 1'b1;

    repeat(2) begin
      for (int i=0; i<30; i++) begin
        @(posedge rclk iff !empty);
        r_en = (i%2 == 0)? 1'b1 : 1'b0;
        if (r_en) begin
          wdata = wdata_q.pop_front();
          if(data_out !== wdata) $error("Time = %0t: Comparison Failed: expected wr_data = %h, rd_data = %h", $time, wdata, data_out);
          else $display("Time = %0t: Comparison Passed: wr_data = %h and rd_data = %h",$time, wdata, data_out);
        end
      end
      #50;
    end

    $finish;
  end
  
  initial begin 
    $dumpfile("dump.vcd"); $dumpvars;
  end
endmodule

fifo/fifo.sim/sim_1/behav/xsim/dump.vcd
$date
   Mon Aug 11 19:50:02 2025
$end
$version
  2020.2
$end
$timescale
  1ps
$end
$scope module async_fifo_TB $end
$var wire 8 ! data_out [7:0] $end
$var wire 1 " full $end
$var wire 1 # empty $end
$var reg 8 $ data_in [7:0] $end
$var reg 1 % w_en $end
$var reg 1 & wclk $end
$var reg 1 ' wrst_n $end
$var reg 1 ( r_en $end
$var reg 1 ) rclk $end
$var reg 1 * rrst_n $end
$var reg 32 + wdata_q $end
$var reg 8 , wdata [7:0] $end
$var parameter 32 - DATA_WIDTH [31:0] $end
$scope module as_fifo $end
$var wire 1 . wclk $end
$var wire 1 / wrst_n $end
$var wire 1 0 rclk $end
$var wire 1 1 rrst_n $end
$var wire 1 2 w_en $end
$var wire 1 3 r_en $end
$var wire 8 4 data_in [7:0] $end
$var reg 8 5 data_out [7:0] $end
$var reg 1 6 full $end
$var reg 1 7 empty $end
$var reg 4 8 g_wptr_sync [3:0] $end
$var reg 4 9 g_rptr_sync [3:0] $end
$var reg 4 : b_wptr [3:0] $end
$var reg 4 ; b_rptr [3:0] $end
$var reg 4 < g_wptr [3:0] $end
$var reg 4 = g_rptr [3:0] $end
$var wire 3 > waddr [2:0] $end
$var wire 3 ? raddr [2:0] $end
$var parameter 32 @ DEPTH [31:0] $end
$var parameter 32 A DATA_WIDTH [31:0] $end
$var parameter 32 B PTR_WIDTH [31:0] $end
$scope module sync_wptr $end
$var wire 1 0 clk $end
$var wire 1 1 rst_n $end
$var wire 4 C d_in [3:0] $end
$var reg 4 8 d_out [3:0] $end
$var reg 4 D q1 [3:0] $end
$var parameter 32 E WIDTH [31:0] $end
$upscope $end
$scope module sync_rptr $end
$var wire 1 . clk $end
$var wire 1 / rst_n $end
$var wire 4 F d_in [3:0] $end
$var reg 4 9 d_out [3:0] $end
$var reg 4 G q1 [3:0] $end
$var parameter 32 H WIDTH [31:0] $end
$upscope $end
$scope module wptr_h $end
$var wire 1 . wclk $end
$var wire 1 / wrst_n $end
$var wire 1 2 w_en $end
$var wire 4 I g_rptr_sync [3:0] $end
$var reg 4 : b_wptr [3:0] $end
$var reg 4 < g_wptr [3:0] $end
$var reg 1 6 full $end
$var reg 4 J b_wptr_next [3:0] $end
$var reg 4 K g_wptr_next [3:0] $end
$var reg 1 L wrap_around $end
$var wire 1 M wfull $end
$var parameter 32 N PTR_WIDTH [31:0] $end
$upscope $end
$scope module rptr_h $end
$var wire 1 0 rclk $end
$var wire 1 1 rrst_n $end
$var wire 1 3 r_en $end
$var wire 4 O g_wptr_sync [3:0] $end
$var reg 4 ; b_rptr [3:0] $end
$var reg 4 = g_rptr [3:0] $end
$var reg 1 7 empty $end
$var reg 4 P b_rptr_next [3:0] $end
$var reg 4 Q g_rptr_next [3:0] $end
$var wire 1 R rempty $end
$var parameter 32 S PTR_WIDTH [31:0] $end
$upscope $end
$scope module fifom $end
$var wire 1 . wclk $end
$var wire 1 2 w_en $end
$var wire 1 0 rclk $end
$var wire 1 3 r_en $end
$var wire 4 T b_wptr [3:0] $end
$var wire 4 U b_rptr [3:0] $end
$var wire 8 4 data_in [7:0] $end
$var wire 1 6 full $end
$var wire 1 7 empty $end
$var reg 8 5 data_out [7:0] $end
$var parameter 32 V DEPTH [31:0] $end
$var parameter 32 W DATA_WIDTH [31:0] $end
$var parameter 32 X PTR_WIDTH [31:0] $end
$upscope $end
$upscope $end
$scope begin Block50_10 $end
$var reg 32 Y i $end
$upscope $end
$scope begin Block70_12 $end
$var reg 32 Z i $end
$upscope $end
$upscope $end
$enddefinitions $end
#0
$dumpvars
bx !
0"
1#
b0 $
0%
0&
0'
0(
0)
0*
b0 +
bx ,
b1000 -
0.
0/
00
01
02
03
b0 4
bx 5
06
17
bx 8
bx 9
b0 :
b0 ;
b0 <
b0 =
bz >
bz ?
b1000 @
b1000 A
b11 B
b0 C
bx D
b11 E
b0 F
bx G
b11 H
bx I
b0 J
b0 K
xL
xM
b11 N
bx O
b0 P
b0 Q
xR
b11 S
b0 T
b0 U
b1000 V
b1000 W
b11 X
b0 Y
b0 Z
$end
#10000
1&
1.
06
b0 9
b0 :
b0 <
b0 G
b0 I
0M
#20000
0&
0.
#30000
1&
1.
06
b0 9
b0 :
b0 <
b0 G
#35000
1)
10
17
b0 8
b0 ;
b0 =
b0 D
b0 O
1R
#40000
0&
0.
#50000
1&
1.
06
b0 9
b0 :
b0 <
b0 G
#60000
0&
0.
#70000
1&
0)
1.
00
06
b0 9
b0 :
b0 <
b0 G
#80000
0&
0.
#90000
1&
1.
06
b0 9
b0 :
b0 <
b0 G
#100000
0&
0.
#105000
1)
10
17
b0 8
b0 ;
b0 =
b0 D
#110000
1&
1.
06
b0 9
b0 :
b0 <
b0 G
#120000
0&
0.
#130000
1&
1.
06
b0 9
b0 :
b0 <
b0 G
#140000
0&
0)
0.
00
#150000
1&
1.
06
b0 9
b0 :
b0 <
b0 G
#160000
0&
0.
#170000
1&
1.
06
b0 9
b0 :
b0 <
b0 G
#175000
1)
10
17
b0 8
b0 ;
b0 =
b0 D
#180000
0&
0.
#190000
1&
1'
1.
1/
06
b0 9
b0 :
b0 <
b0 G
b0 Y
#200000
0&
0.
#210000
b111 !
b111 $
1%
1&
0)
1.
00
12
b111 4
b111 5
06
b0 9
b0 :
b0 <
b0 G
b1 J
b1 K
0M
b1 Y
#220000
0&
0.
#230000
0%
1&
1.
02
06
b0 9
b1 :
b1 <
b1 C
b0 G
b1 J
b1 K
0M
b1 T
b10 Y
#240000
0&
0.
#245000
1)
10
17
b0 8
b0 ;
b0 =
b0 D
#250000
b11010 $
1%
1&
1.
12
b11010 4
b111 5
06
b0 9
b1 :
b1 <
b0 G
b10 J
b11 K
0M
b11 Y
#260000
0&
0.
#270000
0%
1&
1.
02
06
b0 9
b10 :
b11 <
b11 C
b0 G
b10 J
b11 K
0M
b10 T
b100 Y
#280000
0&
0)
0.
00
#290000
b11010001 $
1%
1&
1.
12
b11010001 4
b111 5
06
b0 9
b10 :
b11 <
b0 G
b11 J
b10 K
0M
b101 Y
#300000
0&
0.
#310000
0%
1&
1.
02
06
b0 9
b11 :
b10 <
b10 C
b0 G
b11 J
b10 K
0M
b11 T
b110 Y
#315000
1)
10
17
b0 8
b0 ;
b0 =
b0 D
#320000
0&
0.
#330000
b11000011 $
1%
1&
1.
12
b11000011 4
b111 5
06
b0 9
b11 :
b10 <
b0 G
b100 J
b110 K
0M
b111 Y
#340000
0&
0.
#350000
0%
1&
0)
1.
00
02
06
b0 9
b100 :
b110 <
b110 C
b0 G
b100 J
b110 K
0M
b100 T
b1000 Y
#360000
0&
0.
#370000
b11101010 $
1%
1&
1.
12
b11101010 4
b111 5
06
b0 9
b100 :
b110 <
b0 G
b101 J
b111 K
0M
b1001 Y
#380000
0&
0.
#385000
1)
10
17
b0 8
b0 ;
b0 =
b0 D
#390000
0%
1&
1.
02
06
b0 9
b101 :
b111 <
b111 C
b0 G
b101 J
b111 K
0M
b101 T
b1010 Y
#400000
0&
0.
#410000
b10111101 $
1%
1&
1.
12
b10111101 4
b111 5
06
b0 9
b101 :
b111 <
b0 G
b110 J
b101 K
0M
b1011 Y
#420000
0&
0)
0.
00
#430000
0%
1&
1.
02
06
b0 9
b110 :
b101 <
b101 C
b0 G
b110 J
b101 K
0M
b110 T
b1100 Y
#440000
0&
0.
#450000
b1011001 $
1%
1&
1.
12
b1011001 4
b111 5
06
b0 9
b110 :
b101 <
b0 G
b111 J
b100 K
0M
b1101 Y
#455000
1)
10
17
b0 8
b0 ;
b0 =
b0 D
#460000
0&
0.
#470000
0%
1&
1.
02
06
b0 9
b111 :
b100 <
b100 C
b0 G
b111 J
b100 K
0M
b111 T
b1110 Y
#480000
0&
0.
#490000
b11110010 $
1%
1&
0)
1.
00
12
b11110010 4
b111 5
06
b0 9
b111 :
b100 <
b0 G
b1000 J
b1100 K
1M
b1111 Y
#500000
0&
0.
#510000
1"
0%
1&
1.
02
16
b0 9
b1000 :
b1100 <
b1100 C
b0 G
b1000 J
b1100 K
1M
b1000 T
b10000 Y
#520000
0&
0.
#525000
1)
10
17
b0 8
b0 ;
b0 =
b0 D
#530000
1&
1.
16
b0 9
b1000 :
b1100 <
b0 G
#540000
0&
0.
#550000
1&
1.
16
b0 9
b1000 :
b1100 <
b0 G
#560000
0&
0)
0.
00
#570000
1&
1.
16
b0 9
b1000 :
b1100 <
b0 G
#580000
0&
0.
#590000
1&
1.
16
b0 9
b1000 :
b1100 <
b0 G
#595000
1)
10
17
b0 8
b0 ;
b0 =
b0 D
#600000
0&
0.
#610000
1&
1.
16
b0 9
b1000 :
b1100 <
b0 G
#620000
0&
0.
#630000
1&
0)
1.
00
16
b0 9
b1000 :
b1100 <
b0 G
#640000
0&
0.
#650000
1&
1.
16
b0 9
b1000 :
b1100 <
b0 G
#660000
0&
0.
#665000
1)
10
17
b0 8
b0 ;
b0 =
b0 D
#670000
1&
1.
16
b0 9
b1000 :
b1100 <
b0 G
#680000
0&
0.
#690000
1&
1.
16
b0 9
b1000 :
b1100 <
b0 G
#700000
0&
0)
0.
00
#710000
1&
1.
16
b0 9
b1000 :
b1100 <
b0 G
#720000
0&
0.
#730000
1&
1.
16
b0 9
b1000 :
b1100 <
b0 G
#735000
1)
10
17
b0 8
b0 ;
b0 =
b0 D
#740000
0&
0.
#750000
1&
1.
16
b0 9
b1000 :
b1100 <
b0 G
#760000
0&
0.
#770000
1&
0)
1.
00
16
b0 9
b1000 :
b1100 <
b0 G
#780000
0&
0.
#790000
1&
1.
16
b0 9
b1000 :
b1100 <
b0 G
#800000
0&
0.
#805000
1)
10
17
b0 8
b0 ;
b0 =
b0 D
#810000
1&
1.
16
b0 9
b1000 :
b1100 <
b0 G
#820000
0&
0.
#830000
1&
1.
16
b0 9
b1000 :
b1100 <
b0 G
#840000
0&
0)
0.
00
#850000
1&
1.
16
b0 9
b1000 :
b1100 <
b0 G
#860000
0&
0.
#870000
1&
1.
16
b0 9
b1000 :
b1100 <
b0 G
#875000
1)
10
17
b0 8
b0 ;
b0 =
b0 D
#880000
0&
0.
#890000
1&
1.
16
b0 9
b1000 :
b1100 <
b0 G
#900000
0&
0.
#910000
1&
0)
1.
00
16
b0 9
b1000 :
b1100 <
b0 G
#920000
0&
0.
#930000
1&
1.
16
b0 9
b1000 :
b1100 <
b0 G
#940000
0&
0.
#945000
1)
10
17
b0 8
b0 ;
b0 =
b0 D
#950000
1&
1.
16
b0 9
b1000 :
b1100 <
b0 G
#960000
0&
0.
#970000
1&
1.
16
b0 9
b1000 :
b1100 <
b0 G
#980000
0&
0)
0.
00
#990000
1&
1.
16
b0 9
b1000 :
b1100 <
b0 G
#1000000
0&
0.
#1010000
1&
1.
16
b0 9
b1000 :
b1100 <
b0 G
#1015000
1)
10
17
b0 8
b0 ;
b0 =
b0 D
#1020000
0&
0.
#1030000
1&
1.
16
b0 9
b1000 :
b1100 <
b0 G
#1040000
0&
0.
#1050000
1&
0)
1.
00
16
b0 9
b1000 :
b1100 <
b0 G
#1060000
0&
0.
#1070000
1&
1.
16
b0 9
b1000 :
b1100 <
b0 G
#1080000
0&
0.
#1085000
1)
10
17
b0 8
b0 ;
b0 =
b0 D
#1090000
1&
1.
16
b0 9
b1000 :
b1100 <
b0 G
#1100000
0&
0.
#1110000
1&
1.
16
b0 9
b1000 :
b1100 <
b0 G
#1120000
0&
0)
0.
00
#1130000
1&
1.
16
b0 9
b1000 :
b1100 <
b0 G
#1140000
0&
0.
#1150000
1&
1.
16
b0 9
b1000 :
b1100 <
b0 G
#1155000
1)
10
17
b0 8
b0 ;
b0 =
b0 D
#1160000
0&
0.
#1170000
1&
1.
16
b0 9
b1000 :
b1100 <
b0 G
#1180000
0&
0.
#1190000
1&
0)
1.
00
16
b0 9
b1000 :
b1100 <
b0 G
#1200000
0&
0.
#1210000
1&
1.
16
b0 9
b1000 :
b1100 <
b0 G
#1220000
0&
0.
#1225000
1)
10
17
b0 8
b0 ;
b0 =
b0 D
#1230000
1&
1.
16
b0 9
b1000 :
b1100 <
b0 G
#1240000
0&
0.
#1250000
1&
1.
16
b0 9
b1000 :
b1100 <
b0 G
#1260000
0&
0)
0.
00
#1270000
1&
1.
16
b0 9
b1000 :
b1100 <
b0 G
#1280000
0&
0.
#1290000
1&
1.
16
b0 9
b1000 :
b1100 <
b0 G
#1295000
1)
10
17
b0 8
b0 ;
b0 =
b0 D
#1300000
0&
0.
#1310000
1&
1.
16
b0 9
b1000 :
b1100 <
b0 G
#1320000
0&
0.
#1330000
1&
0)
1.
00
16
b0 9
b1000 :
b1100 <
b0 G
#1340000
0&
0.
#1350000
1&
1.
16
b0 9
b1000 :
b1100 <
b0 G
#1360000
0&
0.
#1365000
1)
1*
10
11
17
b0 8
b0 ;
b0 =
b1100 D
b0 Z
#1370000
1&
1.
16
b0 9
b1000 :
b1100 <
b0 G
#1380000
0&
0.
#1390000
1&
1.
16
b0 9
b1000 :
b1100 <
b0 G
#1400000
0&
0)
0.
00
#1410000
1&
1.
16
b0 9
b1000 :
b1100 <
b0 G
#1420000
0&
0.
#1430000
1&
1.
16
b0 9
b1000 :
b1100 <
b0 G
#1435000
1)
10
17
b1100 8
b0 ;
b0 =
b1100 D
b1100 O
0R
#1440000
0&
0.
#1450000
1&
1.
16
b0 9
b1000 :
b1100 <
b0 G
#1460000
0&
0.
#1470000
1&
0)
1.
00
16
b0 9
b1000 :
b1100 <
b0 G
#1480000
0&
0.
#1490000
1&
1.
16
b0 9
b1000 :
b1100 <
b0 G
#1500000
0&
0.
#1505000
0#
1)
10
07
b1100 8
b0 ;
b0 =
b1100 D
b0 P
#1510000
1&
1.
16
b0 9
b1000 :
b1100 <
b0 G
#1520000
0&
0.
#1530000
1&
1.
16
b0 9
b1000 :
b1100 <
b0 G
#1540000
0&
0)
0.
00
#1550000
1&
1.
16
b0 9
b1000 :
b1100 <
b0 G
#1560000
0&
0.
#1570000
1&
1.
16
b0 9
b1000 :
b1100 <
b0 G
#1575000
1(
1)
b111 ,
10
13
07
b1100 8
b0 ;
b0 =
b1100 D
b1 P
b1 Q
0R
b1 Z
#1580000
0&
0.
#1590000
1&
1.
16
b0 9
b1000 :
b1100 <
b0 G
#1600000
0&
0.
#1610000
1&
0)
1.
00
16
b0 9
b1000 :
b1100 <
b0 G
#1620000
0&
0.
#1630000
1&
1.
16
b0 9
b1000 :
b1100 <
b0 G
#1640000
0&
0.
#1645000
b11010 !
0(
1)
10
03
b11010 5
07
b1100 8
b1 ;
b1 =
b1100 D
b1 F
b1 P
b1 Q
0R
b1 U
b10 Z
#1650000
1&
1.
16
b0 9
b1000 :
b1100 <
b1 G
#1660000
0&
0.
#1670000
1&
1.
16
b1 9
b1000 :
b1100 <
b1 G
b1 I
0M
#1680000
0&
0)
0.
00
#1690000
0"
1&
1.
06
b1 9
b1000 :
b1100 <
b1 G
b1000 J
#1700000
0&
0.
#1710000
b11011000 $
1%
1&
1.
12
b11011000 4
b11010 5
06
b1 9
b1000 :
b1100 <
b1 G
b1001 J
b1101 K
1M
b10001 Y
#1715000
1(
1)
b11010 ,
10
13
07
b1100 8
b1 ;
b1 =
b1100 D
b10 P
b11 Q
0R
b11 Z
#1720000
0&
0.
#1730000
1"
0%
1&
1.
02
16
b1 9
b1001 :
b1101 <
b1101 C
b1 G
b1001 J
b1101 K
1M
b1001 T
b10010 Y
#1740000
0&
0.
#1750000
1&
0)
1.
00
16
b1 9
b1001 :
b1101 <
b1 G
#1760000
0&
0.
#1770000
1&
1.
16
b1 9
b1001 :
b1101 <
b1 G
#1780000
0&
0.
#1785000
b11010001 !
0(
1)
10
03
b11010001 5
07
b1100 8
b10 ;
b11 =
b1101 D
b11 F
b10 P
b11 Q
0R
b10 U
b100 Z
#1790000
1&
1.
16
b1 9
b1001 :
b1101 <
b11 G
#1800000
0&
0.
#1810000
1&
1.
16
b11 9
b1001 :
b1101 <
b11 G
b11 I
0M
#1820000
0&
0)
0.
00
#1830000
0"
1&
1.
06
b11 9
b1001 :
b1101 <
b11 G
b1001 J
#1840000
0&
0.
#1850000
b101010 $
1%
1&
1.
12
b101010 4
b11010001 5
06
b11 9
b1001 :
b1101 <
b11 G
b1010 J
b1111 K
1M
b10011 Y
#1855000
1(
1)
b11010001 ,
10
13
07
b1101 8
b10 ;
b11 =
b1101 D
b1101 O
b11 P
b10 Q
0R
b101 Z
#1860000
0&
0.
#1870000
1"
0%
1&
1.
02
16
b11 9
b1010 :
b1111 <
b1111 C
b11 G
b1010 J
b1111 K
1M
b1010 T
b10100 Y
#1880000
0&
0.
#1890000
1&
0)
1.
00
16
b11 9
b1010 :
b1111 <
b11 G
#1900000
0&
0.
#1910000
1&
1.
16
b11 9
b1010 :
b1111 <
b11 G
#1920000
0&
0.
#1925000
b11000011 !
0(
1)
10
03
b11000011 5
07
b1101 8
b11 ;
b10 =
b1111 D
b10 F
b11 P
b10 Q
0R
b11 U
b110 Z
#1930000
1&
1.
16
b11 9
b1010 :
b1111 <
b10 G
#1940000
0&
0.
#1950000
1&
1.
16
b10 9
b1010 :
b1111 <
b10 G
b10 I
0M
#1960000
0&
0)
0.
00
#1970000
0"
1&
1.
06
b10 9
b1010 :
b1111 <
b10 G
b1010 J
#1980000
0&
0.
#1990000
b10110101 $
1%
1&
1.
12
b10110101 4
b11000011 5
06
b10 9
b1010 :
b1111 <
b10 G
b1011 J
b1110 K
1M
b10101 Y
#1995000
1(
1)
b11000011 ,
10
13
07
b1111 8
b11 ;
b10 =
b1111 D
b1111 O
b100 P
b110 Q
0R
b111 Z
#2000000
0&
0.
#2010000
1"
0%
1&
1.
02
16
b10 9
b1011 :
b1110 <
b1110 C
b10 G
b1011 J
b1110 K
1M
b1011 T
b10110 Y
#2020000
0&
0.
#2030000
1&
0)
1.
00
16
b10 9
b1011 :
b1110 <
b10 G
#2040000
0&
0.
#2050000
1&
1.
16
b10 9
b1011 :
b1110 <
b10 G
#2060000
0&
0.
#2065000
b11101010 !
0(
1)
10
03
b11101010 5
07
b1111 8
b100 ;
b110 =
b1110 D
b110 F
b100 P
b110 Q
0R
b100 U
b1000 Z
#2070000
1&
1.
16
b10 9
b1011 :
b1110 <
b110 G
#2080000
0&
0.
#2090000
1&
1.
16
b110 9
b1011 :
b1110 <
b110 G
b110 I
0M
#2100000
0&
0)
0.
00
#2110000
0"
1&
1.
06
b110 9
b1011 :
b1110 <
b110 G
b1011 J
#2120000
0&
0.
#2130000
b11000010 $
1%
1&
1.
12
b11000010 4
b11101010 5
06
b110 9
b1011 :
b1110 <
b110 G
b1100 J
b1010 K
1M
b10111 Y
#2135000
1(
1)
b11101010 ,
10
13
07
b1110 8
b100 ;
b110 =
b1110 D
b1110 O
b101 P
b111 Q
0R
b1001 Z
#2140000
0&
0.
#2150000
1"
0%
1&
1.
02
16
b110 9
b1100 :
b1010 <
b1010 C
b110 G
b1100 J
b1010 K
1M
b1100 T
b11000 Y
#2160000
0&
0.
#2170000
1&
0)
1.
00
16
b110 9
b1100 :
b1010 <
b110 G
#2180000
0&
0.
#2190000
1&
1.
16
b110 9
b1100 :
b1010 <
b110 G
#2200000
0&
0.
#2205000
b10111101 !
0(
1)
10
03
b10111101 5
07
b1110 8
b101 ;
b111 =
b1010 D
b111 F
b101 P
b111 Q
0R
b101 U
b1010 Z
#2210000
1&
1.
16
b110 9
b1100 :
b1010 <
b111 G
#2220000
0&
0.
#2230000
1&
1.
16
b111 9
b1100 :
b1010 <
b111 G
b111 I
0M
#2240000
0&
0)
0.
00
#2250000
0"
1&
1.
06
b111 9
b1100 :
b1010 <
b111 G
b1100 J
#2260000
0&
0.
#2270000
b11101000 $
1%
1&
1.
12
b11101000 4
b10111101 5
06
b111 9
b1100 :
b1010 <
b111 G
b1101 J
b1011 K
1M
b11001 Y
#2275000
1(
1)
b10111101 ,
10
13
07
b1010 8
b101 ;
b111 =
b1010 D
b1010 O
b110 P
b101 Q
0R
b1011 Z
#2280000
0&
0.
#2290000
1"
0%
1&
1.
02
16
b111 9
b1101 :
b1011 <
b1011 C
b111 G
b1101 J
b1011 K
1M
b1101 T
b11010 Y
#2300000
0&
0.
#2310000
1&
0)
1.
00
16
b111 9
b1101 :
b1011 <
b111 G
#2320000
0&
0.
#2330000
1&
1.
16
b111 9
b1101 :
b1011 <
b111 G
#2340000
0&
0.
#2345000
b1011001 !
0(
1)
10
03
b1011001 5
07
b1010 8
b110 ;
b101 =
b1011 D
b101 F
b110 P
b101 Q
0R
b110 U
b1100 Z
#2350000
1&
1.
16
b111 9
b1101 :
b1011 <
b101 G
#2360000
0&
0.
#2370000
1&
1.
16
b101 9
b1101 :
b1011 <
b101 G
b101 I
0M
#2380000
0&
0)
0.
00
#2390000
0"
1&
1.
06
b101 9
b1101 :
b1011 <
b101 G
b1101 J
#2400000
0&
0.
#2410000
b1111 $
1%
1&
1.
12
b1111 4
b1011001 5
06
b101 9
b1101 :
b1011 <
b101 G
b1110 J
b1001 K
1M
b11011 Y
#2415000
1(
1)
b1011001 ,
10
13
07
b1011 8
b110 ;
b101 =
b1011 D
b1011 O
b111 P
b100 Q
0R
b1101 Z
#2420000
0&
0.
#2430000
1"
0%
1&
1.
02
16
b101 9
b1110 :
b1001 <
b1001 C
b101 G
b1110 J
b1001 K
1M
b1110 T
b11100 Y
#2440000
0&
0.
#2450000
1&
0)
1.
00
16
b101 9
b1110 :
b1001 <
b101 G
